lite_github_mcp/__init__.py
lite_github_mcp/cli.py
lite_github_mcp/schemas/issue.py
lite_github_mcp/schemas/pr.py
lite_github_mcp/schemas/repo.py
lite_github_mcp/server.py
lite_github_mcp/services/analytics.py
lite_github_mcp/services/cache.py
lite_github_mcp/services/gh_cli.py
lite_github_mcp/services/git_cli.py
lite_github_mcp/services/pager.py
lite_github_mcp/tools/router.py
lite_github_mcp/utils/errors.py
lite_github_mcp/utils/subprocess.py
lite_github_mcp-0.4.0.dist-info/WHEEL
lite_github_mcp-0.4.0.dist-info/entry_points.txt
lite_github_mcp-0.4.0.dist-info/METADATA
lite_github_mcp-0.4.0.dist-info/RECORD
