Metadata-Version: 2.3
Name: lite-github-mcp
Version: 0.4.0
Summary: Lightweight GitHub MCP server with minimal context and CLI-first data fetches
Keywords: mcp,github,fastmcp,cli,context-minimization
Author: Gerald Sornsen
License: MIT
Classifier: Programming Language :: Python :: 3
Classifier: License :: OSI Approved :: MIT License
Classifier: Environment :: Console
Requires-Dist: fastmcp>=2.0.0
Requires-Dist: pydantic>=2.7
Requires-Dist: typer>=0.12
Requires-Dist: rapidfuzz>=3.9
Requires-Dist: diskcache>=5.6
Requires-Python: >=3.10
